CongLingdaoYiGoujianJiyuFabricSdkNodeDeXiangmuKaifaShizhan/README.md
CongLingdaoYiGoujianJiyuFabricSdkNodeDeXiangmuKaifaShizhan/__init__.py
CongLingdaoYiGoujianJiyuFabricSdkNodeDeXiangmuKaifaShizhan/__main__.py
CongLingdaoYiGoujianJiyuFabricSdkNodeDeXiangmuKaifaShizhan/file.epub
CongLingdaoYiGoujianJiyuFabricSdkNodeDeXiangmuKaifaShizhan/index.html
CongLingdaoYiGoujianJiyuFabricSdkNodeDeXiangmuKaifaShizhan/css/__init__.py
CongLingdaoYiGoujianJiyuFabricSdkNodeDeXiangmuKaifaShizhan/css/annotations.css
CongLingdaoYiGoujianJiyuFabricSdkNodeDeXiangmuKaifaShizhan/css/main.css
CongLingdaoYiGoujianJiyuFabricSdkNodeDeXiangmuKaifaShizhan/css/normalize.css
CongLingdaoYiGoujianJiyuFabricSdkNodeDeXiangmuKaifaShizhan/css/popup.css
CongLingdaoYiGoujianJiyuFabricSdkNodeDeXiangmuKaifaShizhan/font/__init__.py
CongLingdaoYiGoujianJiyuFabricSdkNodeDeXiangmuKaifaShizhan/font/fontello.eot
CongLingdaoYiGoujianJiyuFabricSdkNodeDeXiangmuKaifaShizhan/font/fontello.svg
CongLingdaoYiGoujianJiyuFabricSdkNodeDeXiangmuKaifaShizhan/font/fontello.ttf
CongLingdaoYiGoujianJiyuFabricSdkNodeDeXiangmuKaifaShizhan/font/fontello.woff
CongLingdaoYiGoujianJiyuFabricSdkNodeDeXiangmuKaifaShizhan/img/__init__.py
CongLingdaoYiGoujianJiyuFabricSdkNodeDeXiangmuKaifaShizhan/img/annotator-glyph-sprite.png
CongLingdaoYiGoujianJiyuFabricSdkNodeDeXiangmuKaifaShizhan/img/annotator-icon-sprite.png
CongLingdaoYiGoujianJiyuFabricSdkNodeDeXiangmuKaifaShizhan/img/apple-touch-icon.png
CongLingdaoYiGoujianJiyuFabricSdkNodeDeXiangmuKaifaShizhan/img/cancelfullscreen.png
CongLingdaoYiGoujianJiyuFabricSdkNodeDeXiangmuKaifaShizhan/img/close.png
CongLingdaoYiGoujianJiyuFabricSdkNodeDeXiangmuKaifaShizhan/img/fullscreen.png
CongLingdaoYiGoujianJiyuFabricSdkNodeDeXiangmuKaifaShizhan/img/loader.gif
CongLingdaoYiGoujianJiyuFabricSdkNodeDeXiangmuKaifaShizhan/img/menu-icon.png
CongLingdaoYiGoujianJiyuFabricSdkNodeDeXiangmuKaifaShizhan/img/save.png
CongLingdaoYiGoujianJiyuFabricSdkNodeDeXiangmuKaifaShizhan/img/saved.png
cong_lingdao_yi_goujian_jiyu_fabric_sdk_node_de_xiangmu_kaifa_shizhan-2024.3.5.0.dist-info/METADATA
cong_lingdao_yi_goujian_jiyu_fabric_sdk_node_de_xiangmu_kaifa_shizhan-2024.3.5.0.dist-info/WHEEL
cong_lingdao_yi_goujian_jiyu_fabric_sdk_node_de_xiangmu_kaifa_shizhan-2024.3.5.0.dist-info/entry_points.txt
cong_lingdao_yi_goujian_jiyu_fabric_sdk_node_de_xiangmu_kaifa_shizhan-2024.3.5.0.dist-info/top_level.txt
cong_lingdao_yi_goujian_jiyu_fabric_sdk_node_de_xiangmu_kaifa_shizhan-2024.3.5.0.dist-info/RECORD
